{ "_t" : "BH.oM.Data.Library.Dataset", "BHoM_Guid" : "9efce764-9f51-4489-b8e7-ccba6e2fd1c6", "Name" : "Distance", "Fragments" : [], "Tags" : [], "CustomData" : { }, "SourceInformation" : { "_t" : "BH.oM.Data.Library.Source", "BHoM_Guid" : "fc8e4d30-6594-4157-a879-e819f13a0c2b", "Name" : "", "Fragments" : [], "Tags" : [], "CustomData" : { }, "SourceLink" : "", "Title" : "Distance", "Author" : "Fraser Greenroyd", "ItemReference" : "", "Version" : "", "Publisher" : "", "Schema" : "", "Language" : "", "Location" : "", "Copyright" : "", "Contributors" : "", "Confidence" : "Medium" }, "TimeOfCreation" : { "$date" : 1665411461754 }, "Data" : [{ "_t" : "BH.oM.Test.UnitTests.UnitTest", "BHoM_Guid" : "7cf4c52d-c3ac-4bae-993f-aef4baf83b8f", "Name" : "", "Fragments" : [], "Tags" : [], "CustomData" : { }, "Method" : { "_t" : "System.Reflection.MethodBase", "TypeName" : "{ \"_t\" : \"System.Type\", \"Name\" : \"BH.Engine.Geometry.Query, Geometry_Engine, Version=6.0.0.0, Culture=neutral, PublicKeyToken=null\", \"_bhomVersion\" : \"6.0\" }", "MethodName" : "Distance", "Parameters" : ["{ \"_t\" : \"System.Type\", \"Name\" : \"BH.oM.Geometry.Point\", \"_bhomVersion\" : \"6.0\" }", "{ \"_t\" : \"System.Type\", \"Name\" : \"BH.oM.Geometry.Point\", \"_bhomVersion\" : \"6.0\" }"], "_bhomVersion" : "6.0" }, "Data" : [{ "_t" : "BH.oM.Test.UnitTests.TestData", "BHoM_Guid" : "e2171ba4-81d2-48e3-bf30-cfb57a497cbc", "Name" : "", "Fragments" : [], "Tags" : [], "CustomData" : { }, "Inputs" : [{ "_t" : "BH.oM.Geometry.Point", "X" : -18.0, "Y" : 11.0, "Z" : 0.0 }, { "_t" : "BH.oM.Geometry.Point", "X" : -13.0, "Y" : 3.0, "Z" : 0.0 }], "Outputs" : [9.4339811320566032] }, { "_t" : "BH.oM.Test.UnitTests.TestData", "BHoM_Guid" : "4e3e872d-850c-4719-bb39-262b5f5e5399", "Name" : "", "Fragments" : [], "Tags" : [], "CustomData" : { }, "Inputs" : [{ "_t" : "BH.oM.Geometry.Point", "X" : -13.0, "Y" : 3.0, "Z" : 0.0 }, { "_t" : "BH.oM.Geometry.Point", "X" : -13.0, "Y" : 3.0, "Z" : 0.0 }], "Outputs" : [0.0] }, { "_t" : "BH.oM.Test.UnitTests.TestData", "BHoM_Guid" : "db481903-ec24-456d-8bc5-851360230ecc", "Name" : "", "Fragments" : [], "Tags" : [], "CustomData" : { }, "Inputs" : [{ "_t" : "BH.oM.Geometry.Point", "X" : 4.0, "Y" : -5.0, "Z" : 0.0 }, { "_t" : "BH.oM.Geometry.Point", "X" : -13.0, "Y" : 3.0, "Z" : 0.0 }], "Outputs" : [18.788294228055936] }, { "_t" : "BH.oM.Test.UnitTests.TestData", "BHoM_Guid" : "2c5cfc74-52b4-46be-aae5-340ae3c93245", "Name" : "", "Fragments" : [], "Tags" : [], "CustomData" : { }, "Inputs" : [{ "_t" : "BH.oM.Geometry.Point", "X" : 14.0, "Y" : 6.0, "Z" : 0.0 }, { "_t" : "BH.oM.Geometry.Point", "X" : -13.0, "Y" : 3.0, "Z" : 0.0 }], "Outputs" : [27.166155414412248] }, { "_t" : "BH.oM.Test.UnitTests.TestData", "BHoM_Guid" : "cebac670-fb23-4533-92fb-5cecf84c4bc0", "Name" : "", "Fragments" : [], "Tags" : [], "CustomData" : { }, "Inputs" : [{ "_t" : "BH.oM.Geometry.Point", "X" : 2.0, "Y" : 10.0, "Z" : 0.0 }, { "_t" : "BH.oM.Geometry.Point", "X" : -13.0, "Y" : 3.0, "Z" : 0.0 }], "Outputs" : [16.552945357246848] }, { "_t" : "BH.oM.Test.UnitTests.TestData", "BHoM_Guid" : "dd8b9fa6-3588-40b4-9e01-092da3f88ce8", "Name" : "", "Fragments" : [], "Tags" : [], "CustomData" : { }, "Inputs" : [{ "_t" : "BH.oM.Geometry.Point", "X" : -4.0, "Y" : -1.0, "Z" : 0.0 }, { "_t" : "BH.oM.Geometry.Point", "X" : -13.0, "Y" : 3.0, "Z" : 0.0 }], "Outputs" : [9.8488578017961039] }, { "_t" : "BH.oM.Test.UnitTests.TestData", "BHoM_Guid" : "20fc25c2-2e3a-4341-8fc4-eb98925708d0", "Name" : "", "Fragments" : [], "Tags" : [], "CustomData" : { }, "Inputs" : [{ "_t" : "BH.oM.Geometry.Point", "X" : -6.0, "Y" : 11.0, "Z" : 0.0 }, { "_t" : "BH.oM.Geometry.Point", "X" : -13.0, "Y" : 3.0, "Z" : 0.0 }], "Outputs" : [10.63014581273465] }] }], "_bhomVersion" : "6.0" }