{ "_t" : "BH.oM.Data.Library.Dataset", "SourceInformation" : { "_t" : "BH.oM.Data.Library.Source", "SourceLink" : "", "Title" : "", "Author" : "Roly Hudson", "ItemReference" : "", "Version" : "", "Publisher" : "", "Schema" : "", "Language" : "", "Location" : "", "Copyright" : "", "Contributors" : "", "Confidence" : "Undefined", "BHoM_Guid" : "28bf21ad-13af-48d3-aa36-d3b841f11049", "Name" : "" }, "TimeOfCreation" : { "$date" : 1612005177306 }, "Data" : [{ "_t" : "BH.oM.Test.UnitTests.UnitTest", "Method" : { "_t" : "System.Reflection.MethodBase", "TypeName" : "{ \"_t\" : \"System.Type\", \"Name\" : \"BH.Engine.Geometry.Query, Geometry_Engine, Version=8.0.0.0, Culture=neutral, PublicKeyToken=null\", \"_bhomVersion\" : \"8.2\" }", "MethodName" : "Normal", "Parameters" : ["{ \"_t\" : \"System.Type\", \"Name\" : \"BH.oM.Geometry.IPolyline\", \"_bhomVersion\" : \"8.2\" }", "{ \"_t\" : \"System.Type\", \"Name\" : \"System.Double, mscorlib, Version=4.0.0.0, Culture=neutral, PublicKeyToken=b77a5c561934e089\", \"_bhomVersion\" : \"8.2\" }"], "_bhomVersion" : "8.2" }, "Data" : [{ "_t" : "BH.oM.Test.UnitTests.TestData", "BHoM_Guid" : "46704a45-da76-4952-8b5b-3cd071d035ec", "Inputs" : [{ "_t" : "BH.oM.Geometry.Polyline", "ControlPoints" : [{ "_t" : "BH.oM.Geometry.Point", "X" : 0.55334267428700645, "Y" : 10.179301620141011, "Z" : -7.0397666481850614 }, { "_t" : "BH.oM.Geometry.Point", "X" : 0.1351804622959083, "Y" : -4.3912019537503699, "Z" : 0.61123980693168067 }, { "_t" : "BH.oM.Geometry.Point", "X" : 14.085802286658328, "Y" : -4.8472758423439881, "Z" : 8.7502961905705021 }, { "_t" : "BH.oM.Geometry.Point", "X" : 16.536707195032847, "Y" : 11.759964441218841, "Z" : 1.1466925755073814 }, { "_t" : "BH.oM.Geometry.Point", "X" : 6.9035323740514247, "Y" : -3.6737462197388133, "Z" : 4.0518555707758352 }, { "_t" : "BH.oM.Geometry.Point", "X" : 0.55334267428700645, "Y" : 10.179301620141011, "Z" : -7.0397666481850614 }] }, 9.9999999999999995E-07], "Outputs" : [{ "_t" : "BH.oM.Geometry.Vector", "X" : -0.44542404051707135, "Y" : 0.426225718241388, "Z" : 0.78735573995434815 }], "Name" : "" }, { "_t" : "BH.oM.Test.UnitTests.TestData", "BHoM_Guid" : "d88d8b4c-55aa-4c29-8220-f8694147ef6c", "Inputs" : [{ "_t" : "BH.oM.Geometry.Polyline", "ControlPoints" : [{ "_t" : "BH.oM.Geometry.Point", "X" : -7.5983736697989732, "Y" : 0.76575776794015038, "Z" : 4.2011579700388362 }, { "_t" : "BH.oM.Geometry.Point", "X" : -6.947151276867201, "Y" : 6.8288725793718639, "Z" : -2.3094142981291061 }, { "_t" : "BH.oM.Geometry.Point", "X" : 8.5041039443348598, "Y" : 5.3435248718370225, "Z" : 6.5697210398727801 }, { "_t" : "BH.oM.Geometry.Point", "X" : 9.0373110175046119, "Y" : 16.133693574826264, "Z" : -5.3087363218591692 }, { "_t" : "BH.oM.Geometry.Point", "X" : -9.2644196980719897, "Y" : 11.393462676222782, "Z" : -8.5208994386472998 }, { "_t" : "BH.oM.Geometry.Point", "X" : -7.5983736697989732, "Y" : 0.76575776794015038, "Z" : 4.2011579700388362 }] }, 9.9999999999999995E-07], "Outputs" : [{ "_t" : "BH.oM.Geometry.Vector", "X" : -0.29624363775941975, "Y" : 0.71355644283755904, "Z" : 0.63488338297050673 }], "Name" : "" }, { "_t" : "BH.oM.Test.UnitTests.TestData", "BHoM_Guid" : "0a50bae9-23b1-4ed0-b677-80bd0ec80d0a", "Inputs" : [{ "_t" : "BH.oM.Geometry.Polyline", "ControlPoints" : [{ "_t" : "BH.oM.Geometry.Point", "X" : -2.5840310687124566, "Y" : 9.6704947152050629, "Z" : 6.7496261050608517 }, { "_t" : "BH.oM.Geometry.Point", "X" : -0.045839508693569231, "Y" : -3.8758730796405843, "Z" : -4.2793453553409035 }, { "_t" : "BH.oM.Geometry.Point", "X" : -6.3255532007970778, "Y" : -0.83177326577068522, "Z" : -7.4180559297690172 }, { "_t" : "BH.oM.Geometry.Point", "X" : 6.8207119828642551, "Y" : -8.1931116131145938, "Z" : -1.8345164728814332 }, { "_t" : "BH.oM.Geometry.Point", "X" : 8.7975681708952003, "Y" : 0.22276082118301666, "Z" : 8.5137233055548887 }, { "_t" : "BH.oM.Geometry.Point", "X" : -2.5840310687124566, "Y" : 9.6704947152050629, "Z" : 6.7496261050608517 }] }, 9.9999999999999995E-07], "Outputs" : [{ "_t" : "BH.oM.Geometry.Vector", "X" : -0.57136911650497735, "Y" : -0.57988440741122826, "Z" : 0.58075072685761697 }], "Name" : "" }, { "_t" : "BH.oM.Test.UnitTests.TestData", "BHoM_Guid" : "9c4409e2-0aa8-414f-90f3-b25b103527f2", "Inputs" : [{ "_t" : "BH.oM.Geometry.Polyline", "ControlPoints" : [{ "_t" : "BH.oM.Geometry.Point", "X" : 5.8643101638152668, "Y" : 19.024379644771017, "Z" : 8.583899943252046 }, { "_t" : "BH.oM.Geometry.Point", "X" : 13.207830422895322, "Y" : 19.192343335329902, "Z" : -0.414077000697606 }, { "_t" : "BH.oM.Geometry.Point", "X" : 13.107716361477886, "Y" : 4.9369690430278252, "Z" : -6.5372555393092835 }, { "_t" : "BH.oM.Geometry.Point", "X" : 4.8892627094024785, "Y" : 8.8126525349026235, "Z" : 5.3135097515582981 }, { "_t" : "BH.oM.Geometry.Point", "X" : 5.6101038163130781, "Y" : 12.534931295248573, "Z" : 6.054182718855345 }, { "_t" : "BH.oM.Geometry.Point", "X" : 5.8643101638152668, "Y" : 19.024379644771017, "Z" : 8.583899943252046 }] }, 9.9999999999999995E-07], "Outputs" : [{ "_t" : "BH.oM.Geometry.Vector", "X" : -0.74929165196943115, "Y" : 0.2657998775246424, "Z" : -0.6065578664866248 }], "Name" : "" }, { "_t" : "BH.oM.Test.UnitTests.TestData", "BHoM_Guid" : "58b5b1d0-34be-48dd-9048-9d2023d9a868", "Inputs" : [{ "_t" : "BH.oM.Geometry.Polyline", "ControlPoints" : [{ "_t" : "BH.oM.Geometry.Point", "X" : 8.9502557977617947, "Y" : 7.4202675707611778, "Z" : -3.8723764979097388 }, { "_t" : "BH.oM.Geometry.Point", "X" : -3.2256117216486553, "Y" : 8.2202925101207818, "Z" : 8.497308828964 }, { "_t" : "BH.oM.Geometry.Point", "X" : 10.592910663939175, "Y" : 16.76289063120641, "Z" : 3.7030190936455072 }, { "_t" : "BH.oM.Geometry.Point", "X" : 8.9502557977617947, "Y" : 7.4202675707611778, "Z" : -3.8723764979097388 }] }, 9.9999999999999995E-07], "Outputs" : [{ "_t" : "BH.oM.Geometry.Vector", "X" : -0.5624810195915666, "Y" : 0.57815446912310475, "Z" : -0.59106049811522032 }], "Name" : "" }, { "_t" : "BH.oM.Test.UnitTests.TestData", "BHoM_Guid" : "a3db0aba-7c6e-4288-88db-f5b690a09b77", "Inputs" : [{ "_t" : "BH.oM.Geometry.Polyline", "ControlPoints" : [{ "_t" : "BH.oM.Geometry.Point", "X" : -0.031922255442148995, "Y" : 9.277161013228131, "Z" : 4.8355785157564144 }, { "_t" : "BH.oM.Geometry.Point", "X" : 2.4465784780769306, "Y" : -1.0579558394149999, "Z" : -5.6970609963860657 }, { "_t" : "BH.oM.Geometry.Point", "X" : 11.3550851030041, "Y" : -0.4702574546379843, "Z" : 7.5159274210805975 }, { "_t" : "BH.oM.Geometry.Point", "X" : 7.0810482280187905, "Y" : -6.588336204254027, "Z" : -6.7218096718242286 }, { "_t" : "BH.oM.Geometry.Point", "X" : -3.5695735804913689, "Y" : 3.9257325395621239, "Z" : -7.3381318022508566 }, { "_t" : "BH.oM.Geometry.Point", "X" : -0.031922255442148995, "Y" : 9.277161013228131, "Z" : 4.8355785157564144 }] }, 9.9999999999999995E-07], "Outputs" : [{ "_t" : "BH.oM.Geometry.Vector", "X" : 0.63791532472744994, "Y" : 0.61937365709151693, "Z" : -0.45764649171489569 }], "Name" : "" }, { "_t" : "BH.oM.Test.UnitTests.TestData", "BHoM_Guid" : "9669dc1f-4e37-480a-a449-922087508783", "Inputs" : [{ "_t" : "BH.oM.Geometry.Polyline", "ControlPoints" : [{ "_t" : "BH.oM.Geometry.Point", "X" : 4.0026463046050385, "Y" : -4.1711786147977534, "Z" : 3.4875032665476571 }, { "_t" : "BH.oM.Geometry.Point", "X" : 3.4179530199502142, "Y" : 0.85296223474154953, "Z" : -8.7348469593072551 }, { "_t" : "BH.oM.Geometry.Point", "X" : 1.8775275592973049, "Y" : 14.809299474910796, "Z" : -9.0601831448589607 }, { "_t" : "BH.oM.Geometry.Point", "X" : 2.0068071661749416, "Y" : 14.076253497939513, "Z" : 10.373817668398308 }, { "_t" : "BH.oM.Geometry.Point", "X" : 3.0514414543683928, "Y" : 4.2302614045324338, "Z" : -6.3020352611316666 }, { "_t" : "BH.oM.Geometry.Point", "X" : 4.0026463046050385, "Y" : -4.1711786147977534, "Z" : 3.4875032665476571 }] }, 9.9999999999999995E-07], "Outputs" : [{ "_t" : "BH.oM.Geometry.Vector", "X" : 0.99396706326636253, "Y" : 0.10965101958098981, "Z" : -0.0024760950087500239 }], "Name" : "" }, { "_t" : "BH.oM.Test.UnitTests.TestData", "BHoM_Guid" : "7ec519c6-d64a-4d3a-b4ad-cdce1967c0e1", "Inputs" : [{ "_t" : "BH.oM.Geometry.Polyline", "ControlPoints" : [{ "_t" : "BH.oM.Geometry.Point", "X" : 19.630781624594427, "Y" : -5.5682721998191234, "Z" : -2.5992824204151632 }, { "_t" : "BH.oM.Geometry.Point", "X" : 12.564449573004664, "Y" : 8.7664447614202992, "Z" : -9.089058474318831 }, { "_t" : "BH.oM.Geometry.Point", "X" : -0.81149145399391287, "Y" : 8.9342336868565795, "Z" : 3.0829772780733866 }, { "_t" : "BH.oM.Geometry.Point", "X" : 7.4741718161260788, "Y" : 1.7293430771578751, "Z" : 1.9830897603492106 }, { "_t" : "BH.oM.Geometry.Point", "X" : 19.630781624594427, "Y" : -5.5682721998191234, "Z" : -2.5992824204151632 }] }, 9.9999999999999995E-07], "Outputs" : [{ "_t" : "BH.oM.Geometry.Vector", "X" : 0.56371856412064225, "Y" : 0.55487904261937082, "Z" : 0.611825652067296 }], "Name" : "" }, { "_t" : "BH.oM.Test.UnitTests.TestData", "BHoM_Guid" : "1ba04883-1ed5-48c5-aa42-0c6bb0166b92", "Inputs" : [{ "_t" : "BH.oM.Geometry.Polyline", "ControlPoints" : [{ "_t" : "BH.oM.Geometry.Point", "X" : 5.8670379348820543, "Y" : -0.74190332862395181, "Z" : 8.3050019661849035 }, { "_t" : "BH.oM.Geometry.Point", "X" : 7.6468350726647119, "Y" : 4.7098429378659477, "Z" : -0.16639832285028755 }, { "_t" : "BH.oM.Geometry.Point", "X" : -1.7102913431836484, "Y" : 9.8549029216869535, "Z" : 5.6518647570584886 }, { "_t" : "BH.oM.Geometry.Point", "X" : -0.9337968900877236, "Y" : 19.591571724709063, "Z" : -6.4713822059904338 }, { "_t" : "BH.oM.Geometry.Point", "X" : 10.966426959477388, "Y" : 7.7327227546375266, "Z" : -7.7831430943377162 }, { "_t" : "BH.oM.Geometry.Point", "X" : 8.8676188651940357, "Y" : 3.0555400062400722, "Z" : 0.2004062264898715 }, { "_t" : "BH.oM.Geometry.Point", "X" : 5.8670379348820543, "Y" : -0.74190332862395181, "Z" : 8.3050019661849035 }] }, 9.9999999999999995E-07], "Outputs" : [{ "_t" : "BH.oM.Geometry.Vector", "X" : -0.63553432818495326, "Y" : -0.58158185685670138, "Z" : -0.50779785493206997 }], "Name" : "" }, { "_t" : "BH.oM.Test.UnitTests.TestData", "BHoM_Guid" : "9120fcbf-316d-4114-84a1-1ac405129ba7", "Inputs" : [{ "_t" : "BH.oM.Geometry.Polyline", "ControlPoints" : [{ "_t" : "BH.oM.Geometry.Point", "X" : -7.502121076001032, "Y" : 9.7433508984399282, "Z" : 8.1271968865961064 }, { "_t" : "BH.oM.Geometry.Point", "X" : 7.8935722904722692, "Y" : 9.9656722206930901, "Z" : 7.0624107329330439 }, { "_t" : "BH.oM.Geometry.Point", "X" : -5.3076399669281056, "Y" : -1.7307914879584114, "Z" : -4.7417005303332269 }, { "_t" : "BH.oM.Geometry.Point", "X" : -7.502121076001032, "Y" : 9.7433508984399282, "Z" : 8.1271968865961064 }] }, 9.9999999999999995E-07], "Outputs" : [{ "_t" : "BH.oM.Geometry.Vector", "X" : -0.05701622542190047, "Y" : 0.74033347814166406, "Z" : -0.66981750587850808 }], "Name" : "" }], "BHoM_Guid" : "f1e4524e-e5b4-4d19-9021-094f4930d32f", "Name" : "" }, { "_t" : "BH.oM.Test.UnitTests.UnitTest", "Method" : { "_t" : "System.Reflection.MethodBase", "TypeName" : "{ \"_t\" : \"System.Type\", \"Name\" : \"BH.Engine.Geometry.Query, Geometry_Engine, Version=8.0.0.0, Culture=neutral, PublicKeyToken=null\", \"_bhomVersion\" : \"8.2\" }", "MethodName" : "Normal", "Parameters" : ["{ \"_t\" : \"System.Type\", \"Name\" : \"BH.oM.Geometry.IPolyCurve\", \"_bhomVersion\" : \"8.2\" }", "{ \"_t\" : \"System.Type\", \"Name\" : \"System.Double, mscorlib, Version=4.0.0.0, Culture=neutral, PublicKeyToken=b77a5c561934e089\", \"_bhomVersion\" : \"8.2\" }"], "_bhomVersion" : "8.2" }, "Data" : [{ "_t" : "BH.oM.Test.UnitTests.TestData", "BHoM_Guid" : "98489342-070d-40ec-ad8f-4750c79cae7e", "Inputs" : [{ "_t" : "BH.oM.Geometry.PolyCurve", "Curves" : [{ "_t" : "BH.oM.Geometry.Line", "Start" : { "_t" : "BH.oM.Geometry.Point", "X" : 16.536707195032847, "Y" : 11.759964441218841, "Z" : 1.1466925755073814 }, "End" : { "_t" : "BH.oM.Geometry.Point", "X" : 0.55334267428700645, "Y" : 10.179301620141011, "Z" : -7.0397666481850614 }, "Infinite" : false }, { "_t" : "BH.oM.Geometry.Line", "Start" : { "_t" : "BH.oM.Geometry.Point", "X" : 0.55334267428700645, "Y" : 10.179301620141011, "Z" : -7.0397666481850614 }, "End" : { "_t" : "BH.oM.Geometry.Point", "X" : 0.1351804622959083, "Y" : -4.3912019537503699, "Z" : 0.61123980693168067 }, "Infinite" : false }, { "_t" : "BH.oM.Geometry.Line", "Start" : { "_t" : "BH.oM.Geometry.Point", "X" : 0.1351804622959083, "Y" : -4.3912019537503699, "Z" : 0.61123980693168067 }, "End" : { "_t" : "BH.oM.Geometry.Point", "X" : 12.338690771973388, "Y" : -0.97581517589421107, "Z" : 5.6661482634257734 }, "Infinite" : false }, { "_t" : "BH.oM.Geometry.Line", "Start" : { "_t" : "BH.oM.Geometry.Point", "X" : 12.338690771973388, "Y" : -0.97581517589421107, "Z" : 5.6661482634257734 }, "End" : { "_t" : "BH.oM.Geometry.Point", "X" : 14.085802286658328, "Y" : -4.8472758423439881, "Z" : 8.7502961905705021 }, "Infinite" : false }, { "_t" : "BH.oM.Geometry.Line", "Start" : { "_t" : "BH.oM.Geometry.Point", "X" : 14.085802286658328, "Y" : -4.8472758423439881, "Z" : 8.7502961905705021 }, "End" : { "_t" : "BH.oM.Geometry.Point", "X" : 16.536707195032847, "Y" : 11.759964441218841, "Z" : 1.1466925755073814 }, "Infinite" : false }] }, 9.9999999999999995E-07], "Outputs" : [{ "_t" : "BH.oM.Geometry.Vector", "X" : -0.44542404051707146, "Y" : 0.42622571824138811, "Z" : 0.78735573995434815 }], "Name" : "" }, { "_t" : "BH.oM.Test.UnitTests.TestData", "BHoM_Guid" : "0d2ef13d-abe1-4fbc-8690-3850675143c4", "Inputs" : [{ "_t" : "BH.oM.Geometry.PolyCurve", "Curves" : [{ "_t" : "BH.oM.Geometry.Polyline", "ControlPoints" : [{ "_t" : "BH.oM.Geometry.Point", "X" : -7.5983736697989732, "Y" : 0.76575776794014949, "Z" : 4.2011579700388371 }, { "_t" : "BH.oM.Geometry.Point", "X" : 1.0265183331056322, "Y" : 4.9407927164430694, "Z" : 3.5332341973775114 }, { "_t" : "BH.oM.Geometry.Point", "X" : 8.5041039443348598, "Y" : 5.3435248718370225, "Z" : 6.5697210398727801 }] }, { "_t" : "BH.oM.Geometry.Arc", "CoordinateSystem" : { "_t" : "BH.oM.Geometry.CoordinateSystem.Cartesian", "X" : { "_t" : "BH.oM.Geometry.Vector", "X" : -0.59103574866986219, "Y" : 0.38520769863830734, "Z" : -0.70872545650910157 }, "Y" : { "_t" : "BH.oM.Geometry.Vector", "X" : 0.75027758255283172, "Y" : 0.58519418298099013, "Z" : -0.30762203647315395 }, "Z" : { "_t" : "BH.oM.Geometry.Vector", "X" : 0.29624363775941986, "Y" : -0.71355644283755892, "Z" : -0.63488338297050673 }, "Origin" : { "_t" : "BH.oM.Geometry.Point", "X" : 15.251680515770399, "Y" : 12.083476683035194, "Z" : 2.1430664996902564 } }, "Radius" : 10.514371613309939, "StartAngle" : -1.7375798395113278, "EndAngle" : 0.0 }, { "_t" : "BH.oM.Geometry.Line", "Start" : { "_t" : "BH.oM.Geometry.Point", "X" : 9.0373110175046119, "Y" : 16.133693574826264, "Z" : -5.3087363218591692 }, "End" : { "_t" : "BH.oM.Geometry.Point", "X" : -9.2644196980719915, "Y" : 11.39346267622278, "Z" : -8.520899438647298 }, "Infinite" : false }, { "_t" : "BH.oM.Geometry.Arc", "CoordinateSystem" : { "_t" : "BH.oM.Geometry.CoordinateSystem.Cartesian", "X" : { "_t" : "BH.oM.Geometry.Vector", "X" : 0.7514964617003369, "Y" : -0.23612006056282236, "Z" : 0.61603602577421013 }, "Y" : { "_t" : "BH.oM.Geometry.Vector", "X" : -0.58948517804855782, "Y" : -0.65960936916088342, "Z" : 0.46628607632679925 }, "Z" : { "_t" : "BH.oM.Geometry.Vector", "X" : 0.29624363775941981, "Y" : -0.71355644283755915, "Z" : -0.63488338297050684 }, "Origin" : { "_t" : "BH.oM.Geometry.Point", "X" : -16.590610948590438, "Y" : 3.5911171928660455, "Z" : -3.1701902642716968 } }, "Radius" : 11.965774607169296, "StartAngle" : -1.5401134402857342, "EndAngle" : 0.0 }] }, 9.9999999999999995E-07], "Outputs" : [{ "_t" : "BH.oM.Geometry.Vector", "X" : -0.2962436377594197, "Y" : 0.71355644283755904, "Z" : 0.63488338297050673 }], "Name" : "" }, { "_t" : "BH.oM.Test.UnitTests.TestData", "BHoM_Guid" : "71e1449c-5447-4175-87ca-df007cb97b25", "Inputs" : [{ "_t" : "BH.oM.Geometry.PolyCurve", "Curves" : [{ "_t" : "BH.oM.Geometry.Polyline", "ControlPoints" : [{ "_t" : "BH.oM.Geometry.Point", "X" : 8.7975681708952003, "Y" : 0.22276082118301666, "Z" : 8.5137233055548887 }, { "_t" : "BH.oM.Geometry.Point", "X" : 1.5816934427698905, "Y" : 4.2334697261247758, "Z" : 5.4191418810893115 }, { "_t" : "BH.oM.Geometry.Point", "X" : -2.5840310687124566, "Y" : 9.6704947152050629, "Z" : 6.7496261050608517 }, { "_t" : "BH.oM.Geometry.Point", "X" : -6.3255532007970778, "Y" : -0.83177326577068522, "Z" : -7.4180559297690172 }, { "_t" : "BH.oM.Geometry.Point", "X" : 6.8207119828642551, "Y" : -8.1931116131145938, "Z" : -1.8345164728814332 }] }, { "_t" : "BH.oM.Geometry.Arc", "CoordinateSystem" : { "_t" : "BH.oM.Geometry.CoordinateSystem.Cartesian", "X" : { "_t" : "BH.oM.Geometry.Vector", "X" : -0.64638610404136743, "Y" : 0.75399778156534858, "Z" : 0.11692882406299765 }, "Y" : { "_t" : "BH.oM.Geometry.Vector", "X" : 0.50568996154417001, "Y" : 0.30857968085384646, "Z" : 0.80564026920058696 }, "Z" : { "_t" : "BH.oM.Geometry.Vector", "X" : 0.57136911650497746, "Y" : 0.57988440741122815, "Z" : -0.58075072685761697 }, "Origin" : { "_t" : "BH.oM.Geometry.Point", "X" : 18.158137904213124, "Y" : -10.696175661179501, "Z" : 6.8204313170153208 } }, "Radius" : 14.481390727296429, "StartAngle" : -0.96854910316281206, "EndAngle" : 0.0 }] }, 9.9999999999999995E-07], "Outputs" : [{ "_t" : "BH.oM.Geometry.Vector", "X" : -0.57136911650497746, "Y" : -0.57988440741122815, "Z" : 0.58075072685761675 }], "Name" : "" }, { "_t" : "BH.oM.Test.UnitTests.TestData", "BHoM_Guid" : "11fe54d5-66a0-4a53-84d8-2bda13125a26", "Inputs" : [{ "_t" : "BH.oM.Geometry.PolyCurve", "Curves" : [{ "_t" : "BH.oM.Geometry.Arc", "CoordinateSystem" : { "_t" : "BH.oM.Geometry.CoordinateSystem.Cartesian", "X" : { "_t" : "BH.oM.Geometry.Vector", "X" : -0.55111751718013624, "Y" : -0.75812750176922594, "Z" : 0.3485859625951031 }, "Y" : { "_t" : "BH.oM.Geometry.Vector", "X" : 0.36719409383338858, "Y" : -0.59547721717042834, "Z" : -0.71454557677228625 }, "Z" : { "_t" : "BH.oM.Geometry.Vector", "X" : 0.74929165196943104, "Y" : -0.26579987752464251, "Z" : 0.60655786648662491 }, "Origin" : { "_t" : "BH.oM.Geometry.Point", "X" : 10.949508900372546, "Y" : 26.019673559346572, "Z" : 5.3674736071048912 } }, "Radius" : 9.2270678721597434, "StartAngle" : 0.0, "EndAngle" : 1.361622326539075 }, { "_t" : "BH.oM.Geometry.Line", "Start" : { "_t" : "BH.oM.Geometry.Point", "X" : 13.207830422895322, "Y" : 19.192343335329902, "Z" : -0.414077000697606 }, "End" : { "_t" : "BH.oM.Geometry.Point", "X" : 13.107716361477886, "Y" : 4.9369690430278252, "Z" : -6.5372555393092835 }, "Infinite" : false }, { "_t" : "BH.oM.Geometry.Arc", "CoordinateSystem" : { "_t" : "BH.oM.Geometry.CoordinateSystem.Cartesian", "X" : { "_t" : "BH.oM.Geometry.Vector", "X" : 0.62718892464374265, "Y" : 0.57885162372347088, "Z" : -0.52111884490673266 }, "Y" : { "_t" : "BH.oM.Geometry.Vector", "X" : -0.21259368074603435, "Y" : 0.77089637618851636, "Z" : 0.60043542874006584 }, "Z" : { "_t" : "BH.oM.Geometry.Vector", "X" : 0.74929165196943126, "Y" : -0.26579987752464235, "Z" : 0.60655786648662491 }, "Origin" : { "_t" : "BH.oM.Geometry.Point", "X" : -1.1993939224996577, "Y" : -8.2674956617265778, "Z" : 5.3502387900502768 } }, "Radius" : 22.811484262264841, "StartAngle" : 0.0, "EndAngle" : 0.68038911315801909 }, { "_t" : "BH.oM.Geometry.Polyline", "ControlPoints" : [{ "_t" : "BH.oM.Geometry.Point", "X" : 6.871075816491989, "Y" : 13.059532183070901, "Z" : 4.7263672112701016 }, { "_t" : "BH.oM.Geometry.Point", "X" : 4.8892627094024785, "Y" : 8.8126525349026235, "Z" : 5.3135097515582981 }, { "_t" : "BH.oM.Geometry.Point", "X" : 5.8643101638152668, "Y" : 19.024379644771017, "Z" : 8.583899943252046 }] }] }, 9.9999999999999995E-07], "Outputs" : [{ "_t" : "BH.oM.Geometry.Vector", "X" : -0.74929165196943093, "Y" : 0.26579987752464279, "Z" : -0.6065578664866248 }], "Name" : "" }, { "_t" : "BH.oM.Test.UnitTests.TestData", "BHoM_Guid" : "63c6de7e-c0d5-4172-9642-0bfac7c7de6f", "Inputs" : [{ "_t" : "BH.oM.Geometry.PolyCurve", "Curves" : [{ "_t" : "BH.oM.Geometry.Polyline", "ControlPoints" : [{ "_t" : "BH.oM.Geometry.Point", "X" : 8.9502557977617947, "Y" : 7.4202675707611787, "Z" : -3.8723764979097379 }, { "_t" : "BH.oM.Geometry.Point", "X" : -3.2256117216486553, "Y" : 8.2202925101207818, "Z" : 8.497308828964 }, { "_t" : "BH.oM.Geometry.Point", "X" : 10.592910663939175, "Y" : 16.76289063120641, "Z" : 3.7030190936455072 }] }, { "_t" : "BH.oM.Geometry.Arc", "CoordinateSystem" : { "_t" : "BH.oM.Geometry.CoordinateSystem.Cartesian", "X" : { "_t" : "BH.oM.Geometry.Vector", "X" : -0.65104113364356619, "Y" : -0.75036852755074379, "Z" : -0.11442252909907659 }, "Y" : { "_t" : "BH.oM.Geometry.Vector", "X" : 0.50966709223112672, "Y" : -0.32044419591296969, "Z" : -0.79847039544516518 }, "Z" : { "_t" : "BH.oM.Geometry.Vector", "X" : 0.56248101959156682, "Y" : -0.57815446912310486, "Z" : 0.59106049811522043 }, "Origin" : { "_t" : "BH.oM.Geometry.Point", "X" : 14.312246949664232, "Y" : 13.600321637200439, "Z" : -2.92998967025432 } }, "Radius" : 8.2360251523493364, "StartAngle" : -1.657185284821449, "EndAngle" : 0.0 }] }, 9.9999999999999995E-07], "Outputs" : [{ "_t" : "BH.oM.Geometry.Vector", "X" : -0.56248101959156671, "Y" : 0.57815446912310453, "Z" : -0.59106049811522066 }], "Name" : "" }, { "_t" : "BH.oM.Test.UnitTests.TestData", "BHoM_Guid" : "1801a237-cdf8-4f46-b4c2-f2cfb1ebf394", "Inputs" : [{ "_t" : "BH.oM.Geometry.PolyCurve", "Curves" : [{ "_t" : "BH.oM.Geometry.Polyline", "ControlPoints" : [{ "_t" : "BH.oM.Geometry.Point", "X" : 7.0810482280187745, "Y" : -6.5883362042540119, "Z" : -6.7218096718242286 }, { "_t" : "BH.oM.Geometry.Point", "X" : -3.5695735804913689, "Y" : 3.9257325395621239, "Z" : -7.3381318022508566 }, { "_t" : "BH.oM.Geometry.Point", "X" : -0.031922255442148995, "Y" : 9.277161013228131, "Z" : 4.8355785157564144 }, { "_t" : "BH.oM.Geometry.Point", "X" : 7.4462788653391447, "Y" : -1.8776431170291152, "Z" : 0.1626862928900572 }, { "_t" : "BH.oM.Geometry.Point", "X" : 11.3550851030041, "Y" : -0.4702574546379843, "Z" : 7.5159274210805975 }] }, { "_t" : "BH.oM.Geometry.Arc", "CoordinateSystem" : { "_t" : "BH.oM.Geometry.CoordinateSystem.Cartesian", "X" : { "_t" : "BH.oM.Geometry.Vector", "X" : -0.73037173951459411, "Y" : 0.67500511254799012, "Z" : -0.10452377792876283 }, "Y" : { "_t" : "BH.oM.Geometry.Vector", "X" : 0.24417444705844665, "Y" : 0.40092938397572631, "Z" : 0.8829691209031868 }, "Z" : { "_t" : "BH.oM.Geometry.Vector", "X" : 0.63791532472745005, "Y" : 0.61937365709151704, "Z" : -0.45764649171489585 }, "Origin" : { "_t" : "BH.oM.Geometry.Point", "X" : 203.64732944518107, "Y" : -188.25369590767286, "Z" : 21.40886572900687 } }, "Radius" : 269.13182778375364, "StartAngle" : -6.2234466599407305, "EndAngle" : 0.0 }] }, 9.9999999999999995E-07], "Outputs" : [{ "_t" : "BH.oM.Geometry.Vector", "X" : 0.63791532472744994, "Y" : 0.61937365709151693, "Z" : -0.45764649171489569 }], "Name" : "" }, { "_t" : "BH.oM.Test.UnitTests.TestData", "BHoM_Guid" : "af53bf4e-8d0b-402d-aa38-c736a7a508bc", "Inputs" : [{ "_t" : "BH.oM.Geometry.PolyCurve", "Curves" : [{ "_t" : "BH.oM.Geometry.Arc", "CoordinateSystem" : { "_t" : "BH.oM.Geometry.CoordinateSystem.Cartesian", "X" : { "_t" : "BH.oM.Geometry.Vector", "X" : 0.069473361109247164, "Y" : -0.61197345269033343, "Z" : 0.78782101095265056 }, "Y" : { "_t" : "BH.oM.Geometry.Vector", "X" : -0.08487007268659022, "Y" : 0.78324015927882662, "Z" : 0.61589928044693421 }, "Z" : { "_t" : "BH.oM.Geometry.Vector", "X" : -0.99396706326636253, "Y" : -0.1096510195809898, "Z" : 0.0024760950087500053 }, "Origin" : { "_t" : "BH.oM.Geometry.Point", "X" : 2.1919842969731214, "Y" : 11.921430435172908, "Z" : -10.715266870321715 } }, "Radius" : 3.3433475393440659, "StartAngle" : 0.0, "EndAngle" : 1.716445462917725 }, { "_t" : "BH.oM.Geometry.Polyline", "ControlPoints" : [{ "_t" : "BH.oM.Geometry.Point", "X" : 1.8775275592973049, "Y" : 14.809299474910796, "Z" : -9.0601831448589607 }, { "_t" : "BH.oM.Geometry.Point", "X" : 2.0068071661749416, "Y" : 14.076253497939513, "Z" : 10.373817668398308 }, { "_t" : "BH.oM.Geometry.Point", "X" : 4.0026463046050385, "Y" : -4.1711786147977534, "Z" : 3.4875032665476571 }, { "_t" : "BH.oM.Geometry.Point", "X" : 3.4179530199502142, "Y" : 0.85296223474154953, "Z" : -8.7348469593072551 }, { "_t" : "BH.oM.Geometry.Point", "X" : 2.4242578878876846, "Y" : 9.8753904979767881, "Z" : -8.0813074319096163 }] }] }, 9.9999999999999995E-07], "Outputs" : [{ "_t" : "BH.oM.Geometry.Vector", "X" : 0.99396706326636253, "Y" : 0.10965101958098979, "Z" : -0.0024760950087500174 }], "Name" : "" }, { "_t" : "BH.oM.Test.UnitTests.TestData", "BHoM_Guid" : "ad072156-2f32-4a54-acf4-319233aa334b", "Inputs" : [{ "_t" : "BH.oM.Geometry.PolyCurve", "Curves" : [{ "_t" : "BH.oM.Geometry.Polyline", "ControlPoints" : [{ "_t" : "BH.oM.Geometry.Point", "X" : 19.630781624594434, "Y" : -5.568272199819094, "Z" : -2.5992824204151965 }, { "_t" : "BH.oM.Geometry.Point", "X" : 12.564449573004664, "Y" : 8.7664447614202992, "Z" : -9.089058474318831 }, { "_t" : "BH.oM.Geometry.Point", "X" : -0.81149145399391287, "Y" : 8.9342336868565795, "Z" : 3.0829772780733866 }, { "_t" : "BH.oM.Geometry.Point", "X" : 7.4741718161260788, "Y" : 1.7293430771578751, "Z" : 1.9830897603492106 }] }, { "_t" : "BH.oM.Geometry.Arc", "CoordinateSystem" : { "_t" : "BH.oM.Geometry.CoordinateSystem.Cartesian", "X" : { "_t" : "BH.oM.Geometry.Vector", "X" : 0.13568621201906214, "Y" : 0.66846379868109662, "Z" : -0.73126288140500917 }, "Y" : { "_t" : "BH.oM.Geometry.Vector", "X" : 0.81474574704853764, "Y" : -0.4952427666454593, "Z" : -0.30153601733735164 }, "Z" : { "_t" : "BH.oM.Geometry.Vector", "X" : -0.56371856412064214, "Y" : -0.55487904261937093, "Z" : -0.611825652067296 }, "Origin" : { "_t" : "BH.oM.Geometry.Point", "X" : -103.62814449073983, "Y" : -612.80852709641533, "Z" : 661.6883863762024 } }, "Radius" : 908.41157904841418, "StartAngle" : -0.016403419061248668, "EndAngle" : 0.0 }] }, 9.9999999999999995E-07], "Outputs" : [{ "_t" : "BH.oM.Geometry.Vector", "X" : 0.56371856412064436, "Y" : 0.55487904261936949, "Z" : 0.61182565206729522 }], "Name" : "" }, { "_t" : "BH.oM.Test.UnitTests.TestData", "BHoM_Guid" : "35425017-06bc-4876-8fbf-dddd34b9fe1e", "Inputs" : [{ "_t" : "BH.oM.Geometry.PolyCurve", "Curves" : [{ "_t" : "BH.oM.Geometry.Polyline", "ControlPoints" : [{ "_t" : "BH.oM.Geometry.Point", "X" : 10.966426959477388, "Y" : 7.7327227546375266, "Z" : -7.7831430943377162 }, { "_t" : "BH.oM.Geometry.Point", "X" : 8.8676188651940357, "Y" : 3.0555400062400722, "Z" : 0.2004062264898715 }, { "_t" : "BH.oM.Geometry.Point", "X" : 5.8670379348820543, "Y" : -0.74190332862395181, "Z" : 8.3050019661849035 }, { "_t" : "BH.oM.Geometry.Point", "X" : -0.36614941084939723, "Y" : 13.897861746915632, "Z" : -0.66080436824093824 }, { "_t" : "BH.oM.Geometry.Point", "X" : -1.7102913431836484, "Y" : 9.8549029216869535, "Z" : 5.6518647570584886 }, { "_t" : "BH.oM.Geometry.Point", "X" : -0.9337968900877236, "Y" : 19.591571724709063, "Z" : -6.4713822059904338 }] }, { "_t" : "BH.oM.Geometry.Arc", "CoordinateSystem" : { "_t" : "BH.oM.Geometry.CoordinateSystem.Cartesian", "X" : { "_t" : "BH.oM.Geometry.Vector", "X" : 0.12203933835495474, "Y" : -0.72511060721511034, "Z" : 0.67773225332576503 }, "Y" : { "_t" : "BH.oM.Geometry.Vector", "X" : 0.76236639327319844, "Y" : -0.36875079807268951, "Z" : -0.53180854762627638 }, "Z" : { "_t" : "BH.oM.Geometry.Vector", "X" : 0.63553432818495326, "Y" : 0.58158185685670138, "Z" : 0.50779785493207008 }, "Origin" : { "_t" : "BH.oM.Geometry.Point", "X" : 9.0752261698653545, "Y" : 18.969507314487625, "Z" : -18.285721934181055 } }, "Radius" : 15.496648991257427, "StartAngle" : -1.1497021641271308, "EndAngle" : 0.0 }] }, 9.9999999999999995E-07], "Outputs" : [{ "_t" : "BH.oM.Geometry.Vector", "X" : -0.63553432818495337, "Y" : -0.58158185685670138, "Z" : -0.50779785493206997 }], "Name" : "" }, { "_t" : "BH.oM.Test.UnitTests.TestData", "BHoM_Guid" : "1301eec1-8ae0-45ab-a63e-a6b5fe612f7c", "Inputs" : [{ "_t" : "BH.oM.Geometry.PolyCurve", "Curves" : [{ "_t" : "BH.oM.Geometry.Polyline", "ControlPoints" : [{ "_t" : "BH.oM.Geometry.Point", "X" : -7.502121076001032, "Y" : 9.7433508984399282, "Z" : 8.1271968865961064 }, { "_t" : "BH.oM.Geometry.Point", "X" : 7.8935722904722692, "Y" : 9.9656722206930901, "Z" : 7.0624107329330439 }, { "_t" : "BH.oM.Geometry.Point", "X" : -5.3076399669281056, "Y" : -1.7307914879584114, "Z" : -4.7417005303332269 }] }, { "_t" : "BH.oM.Geometry.Arc", "CoordinateSystem" : { "_t" : "BH.oM.Geometry.CoordinateSystem.Cartesian", "X" : { "_t" : "BH.oM.Geometry.Vector", "X" : 0.78572325087700279, "Y" : 0.4471906082385827, "Z" : 0.42738686565508882 }, "Y" : { "_t" : "BH.oM.Geometry.Vector", "X" : -0.61594490262515655, "Y" : 0.5019232023386373, "Z" : 0.6071943477044347 }, "Z" : { "_t" : "BH.oM.Geometry.Vector", "X" : 0.057016225421900463, "Y" : -0.74033347814166417, "Z" : 0.66981750587850808 }, "Origin" : { "_t" : "BH.oM.Geometry.Point", "X" : -20.826184572476826, "Y" : 2.1600242595146963, "Z" : 0.8796962822903347 } }, "Radius" : 16.957705504582993, "StartAngle" : -1.0761054337612082, "EndAngle" : 0.0 }] }, 9.9999999999999995E-07], "Outputs" : [{ "_t" : "BH.oM.Geometry.Vector", "X" : -0.057016225421900706, "Y" : 0.74033347814166406, "Z" : -0.66981750587850797 }], "Name" : "" }], "BHoM_Guid" : "92359519-61d9-4276-b987-afb8e63c69d1", "Name" : "" }, { "_t" : "BH.oM.Test.UnitTests.UnitTest", "Method" : { "_t" : "System.Reflection.MethodBase", "TypeName" : "{ \"_t\" : \"System.Type\", \"Name\" : \"BH.Engine.Geometry.Query, Geometry_Engine, Version=8.0.0.0, Culture=neutral, PublicKeyToken=null\", \"_bhomVersion\" : \"8.2\" }", "MethodName" : "Normal", "Parameters" : ["{ \"_t\" : \"System.Type\", \"Name\" : \"BH.oM.Geometry.Circle\", \"_bhomVersion\" : \"8.2\" }", "{ \"_t\" : \"System.Type\", \"Name\" : \"System.Double, mscorlib, Version=4.0.0.0, Culture=neutral, PublicKeyToken=b77a5c561934e089\", \"_bhomVersion\" : \"8.2\" }"], "_bhomVersion" : "8.2" }, "Data" : [{ "_t" : "BH.oM.Test.UnitTests.TestData", "BHoM_Guid" : "d4fbaaa7-08f3-4e01-acf4-985c7318014a", "Inputs" : [{ "_t" : "BH.oM.Geometry.Circle", "Centre" : { "_t" : "BH.oM.Geometry.Point", "X" : 4.5248653993591965, "Y" : 6.3465071918193745, "Z" : 5.3604537878932685 }, "Normal" : { "_t" : "BH.oM.Geometry.Vector", "X" : 0.47832780743340986, "Y" : 0.67089528681963451, "Z" : 0.56665864747583883 }, "Radius" : 7.2624326996795983 }, 9.9999999999999995E-07], "Outputs" : [{ "_t" : "BH.oM.Geometry.Vector", "X" : 0.47832780743340986, "Y" : 0.67089528681963451, "Z" : 0.56665864747583883 }], "Name" : "" }, { "_t" : "BH.oM.Test.UnitTests.TestData", "BHoM_Guid" : "35c86dfe-f66b-4378-a897-2286a96db6e5", "Inputs" : [{ "_t" : "BH.oM.Geometry.Circle", "Centre" : { "_t" : "BH.oM.Geometry.Point", "X" : 3.5701094444701948, "Y" : -8.1204391914049339, "Z" : -7.0180513416501 }, "Normal" : { "_t" : "BH.oM.Geometry.Vector", "X" : 0.19044523289171822, "Y" : -0.96257629979943016, "Z" : 0.19281462686543516 }, "Radius" : 8.1732535959096868 }, 9.9999999999999995E-07], "Outputs" : [{ "_t" : "BH.oM.Geometry.Vector", "X" : 0.19044523289171822, "Y" : -0.96257629979943016, "Z" : 0.19281462686543516 }], "Name" : "" }, { "_t" : "BH.oM.Test.UnitTests.TestData", "BHoM_Guid" : "d22012a1-4d5f-4d4c-9f5c-c7fe1175dc25", "Inputs" : [{ "_t" : "BH.oM.Geometry.Circle", "Centre" : { "_t" : "BH.oM.Geometry.Point", "X" : -9.5337750108604205, "Y" : -8.0542815560727767, "Z" : 7.5582116830899437 }, "Normal" : { "_t" : "BH.oM.Geometry.Vector", "X" : 0.64501160525895307, "Y" : -0.091855804396661286, "Z" : 0.75863201901838462 }, "Radius" : 7.6802268939466343 }, 9.9999999999999995E-07], "Outputs" : [{ "_t" : "BH.oM.Geometry.Vector", "X" : 0.64501160525895307, "Y" : -0.091855804396661286, "Z" : 0.75863201901838462 }], "Name" : "" }, { "_t" : "BH.oM.Test.UnitTests.TestData", "BHoM_Guid" : "dc00b4e7-f140-4238-b8fd-4b5ecde80e07", "Inputs" : [{ "_t" : "BH.oM.Geometry.Circle", "Centre" : { "_t" : "BH.oM.Geometry.Point", "X" : -6.8571314014760461, "Y" : 5.4451397412666775, "Z" : -8.1744860383563136 }, "Normal" : { "_t" : "BH.oM.Geometry.Vector", "X" : -0.73196484659974126, "Y" : -0.67309007853979796, "Z" : -0.10572232268308282 }, "Radius" : 5.5816119143653715 }, 9.9999999999999995E-07], "Outputs" : [{ "_t" : "BH.oM.Geometry.Vector", "X" : -0.73196484659974126, "Y" : -0.67309007853979796, "Z" : -0.10572232268308282 }], "Name" : "" }, { "_t" : "BH.oM.Test.UnitTests.TestData", "BHoM_Guid" : "b55596b1-12ad-4643-b51c-056600853243", "Inputs" : [{ "_t" : "BH.oM.Geometry.Circle", "Centre" : { "_t" : "BH.oM.Geometry.Point", "X" : 9.8532453644337323, "Y" : 3.7773455650440173, "Z" : -8.9699102840246212 }, "Normal" : { "_t" : "BH.oM.Geometry.Vector", "X" : 0.26479026375271292, "Y" : -0.060854923681583066, "Z" : 0.96238391221252106 }, "Radius" : 2.0603315402103268 }, 9.9999999999999995E-07], "Outputs" : [{ "_t" : "BH.oM.Geometry.Vector", "X" : 0.26479026375271292, "Y" : -0.060854923681583066, "Z" : 0.96238391221252106 }], "Name" : "" }, { "_t" : "BH.oM.Test.UnitTests.TestData", "BHoM_Guid" : "5d272cf7-2369-4650-ba98-2042a7149b03", "Inputs" : [{ "_t" : "BH.oM.Geometry.Circle", "Centre" : { "_t" : "BH.oM.Geometry.Point", "X" : 8.4981101278672497, "Y" : -9.5995974259449159, "Z" : 6.4481933305264425 }, "Normal" : { "_t" : "BH.oM.Geometry.Vector", "X" : -0.60769493615752113, "Y" : 0.46889912580053694, "Z" : 0.64096838798180877 }, "Radius" : 5.5888479461841509 }, 9.9999999999999995E-07], "Outputs" : [{ "_t" : "BH.oM.Geometry.Vector", "X" : -0.60769493615752113, "Y" : 0.46889912580053694, "Z" : 0.64096838798180877 }], "Name" : "" }, { "_t" : "BH.oM.Test.UnitTests.TestData", "BHoM_Guid" : "da7a5351-8a69-450c-93d4-cf3ac2b35b71", "Inputs" : [{ "_t" : "BH.oM.Geometry.Circle", "Centre" : { "_t" : "BH.oM.Geometry.Point", "X" : -9.6987782417325192, "Y" : -8.152743176628249, "Z" : -8.815680434375853 }, "Normal" : { "_t" : "BH.oM.Geometry.Vector", "X" : 0.43461231038758463, "Y" : -0.45479267718200744, "Z" : 0.7773517610716455 }, "Radius" : 9.060270660119258 }, 9.9999999999999995E-07], "Outputs" : [{ "_t" : "BH.oM.Geometry.Vector", "X" : 0.43461231038758463, "Y" : -0.45479267718200744, "Z" : 0.7773517610716455 }], "Name" : "" }, { "_t" : "BH.oM.Test.UnitTests.TestData", "BHoM_Guid" : "1f15fe74-0cd1-43fa-b95b-5a5c84de42bf", "Inputs" : [{ "_t" : "BH.oM.Geometry.Circle", "Centre" : { "_t" : "BH.oM.Geometry.Point", "X" : -9.9683606903852713, "Y" : 2.4299492931132889, "Z" : 8.5246894687994796 }, "Normal" : { "_t" : "BH.oM.Geometry.Vector", "X" : 0.45640611395939001, "Y" : 0.64503953494379973, "Z" : -0.61287638027580649 }, "Radius" : 4.4217787331071587 }, 9.9999999999999995E-07], "Outputs" : [{ "_t" : "BH.oM.Geometry.Vector", "X" : 0.45640611395939001, "Y" : 0.64503953494379973, "Z" : -0.61287638027580649 }], "Name" : "" }, { "_t" : "BH.oM.Test.UnitTests.TestData", "BHoM_Guid" : "856a87ed-3467-43ca-baec-889c69441fb9", "Inputs" : [{ "_t" : "BH.oM.Geometry.Circle", "Centre" : { "_t" : "BH.oM.Geometry.Point", "X" : -0.37073839938768227, "Y" : -0.56009561315183287, "Z" : -0.60605804929791862 }, "Normal" : { "_t" : "BH.oM.Geometry.Vector", "X" : 0.41778079512012367, "Y" : 0.054920981601832078, "Z" : 0.90688637271087513 }, "Radius" : 9.775497531413798 }, 9.9999999999999995E-07], "Outputs" : [{ "_t" : "BH.oM.Geometry.Vector", "X" : 0.41778079512012367, "Y" : 0.054920981601832078, "Z" : 0.90688637271087513 }], "Name" : "" }, { "_t" : "BH.oM.Test.UnitTests.TestData", "BHoM_Guid" : "27114f70-ca8f-48f2-9575-7879b1645574", "Inputs" : [{ "_t" : "BH.oM.Geometry.Circle", "Centre" : { "_t" : "BH.oM.Geometry.Point", "X" : -1.4699410700564925, "Y" : -2.9194121681709824, "Z" : 8.6973908444388712 }, "Normal" : { "_t" : "BH.oM.Geometry.Vector", "X" : 0.40665937458804086, "Y" : 0.10147056045397758, "Z" : -0.90792724291146765 }, "Radius" : 2.7370445768987035 }, 9.9999999999999995E-07], "Outputs" : [{ "_t" : "BH.oM.Geometry.Vector", "X" : 0.40665937458804086, "Y" : 0.10147056045397758, "Z" : -0.90792724291146765 }], "Name" : "" }], "BHoM_Guid" : "6f6aaf11-cdcd-4d11-99cb-c0c21d1ec843", "Name" : "" }, { "_t" : "BH.oM.Test.UnitTests.UnitTest", "Method" : { "_t" : "System.Reflection.MethodBase", "TypeName" : "{ \"_t\" : \"System.Type\", \"Name\" : \"BH.Engine.Geometry.Query, Geometry_Engine, Version=8.0.0.0, Culture=neutral, PublicKeyToken=null\", \"_bhomVersion\" : \"8.2\" }", "MethodName" : "Normal", "Parameters" : ["{ \"_t\" : \"System.Type\", \"Name\" : \"BH.oM.Geometry.Arc\", \"_bhomVersion\" : \"8.2\" }", "{ \"_t\" : \"System.Type\", \"Name\" : \"System.Double, mscorlib, Version=4.0.0.0, Culture=neutral, PublicKeyToken=b77a5c561934e089\", \"_bhomVersion\" : \"8.2\" }"], "_bhomVersion" : "8.2" }, "Data" : [{ "_t" : "BH.oM.Test.UnitTests.TestData", "BHoM_Guid" : "db7b8985-21a6-439a-86c5-571549d3729b", "Inputs" : [{ "_t" : "BH.oM.Geometry.Arc", "CoordinateSystem" : { "_t" : "BH.oM.Geometry.CoordinateSystem.Cartesian", "X" : { "_t" : "BH.oM.Geometry.Vector", "X" : 0.4221749318511609, "Y" : 0.77718664733943477, "Z" : 0.46663609173933035 }, "Y" : { "_t" : "BH.oM.Geometry.Vector", "X" : -0.6587800129014173, "Y" : -0.090574244016791206, "Z" : 0.74686357584393892 }, "Z" : { "_t" : "BH.oM.Geometry.Vector", "X" : 0.62271760977033241, "Y" : -0.62271760977033219, "Z" : 0.47375685426582287 }, "Origin" : { "_t" : "BH.oM.Geometry.Point", "X" : 0.65027026118065689, "Y" : -0.78627919138608449, "Z" : 1.0778074345819126 } }, "Radius" : 9.177700630374094, "StartAngle" : 0.0, "EndAngle" : 4.4382899292537266 }, 9.9999999999999995E-07], "Outputs" : [{ "_t" : "BH.oM.Geometry.Vector", "X" : 0.62271760977033241, "Y" : -0.62271760977033219, "Z" : 0.47375685426582287 }], "Name" : "" }, { "_t" : "BH.oM.Test.UnitTests.TestData", "BHoM_Guid" : "4c54f79e-6e2f-4c0f-91de-a67cc6da7f12", "Inputs" : [{ "_t" : "BH.oM.Geometry.Arc", "CoordinateSystem" : { "_t" : "BH.oM.Geometry.CoordinateSystem.Cartesian", "X" : { "_t" : "BH.oM.Geometry.Vector", "X" : 0.36659024459977507, "Y" : -0.73595168211496076, "Z" : -0.56919830828669604 }, "Y" : { "_t" : "BH.oM.Geometry.Vector", "X" : 0.55980147230432975, "Y" : 0.66313289071548831, "Z" : -0.49686726684017435 }, "Z" : { "_t" : "BH.oM.Geometry.Vector", "X" : 0.74312442038341175, "Y" : -0.13649135812746502, "Z" : 0.65508488380234986 }, "Origin" : { "_t" : "BH.oM.Geometry.Point", "X" : -0.97966378207970539, "Y" : 1.0135007010126689, "Z" : 0.046302556985792526 } }, "Radius" : 12.411059196398192, "StartAngle" : 0.0, "EndAngle" : 4.3894871172047631 }, 9.9999999999999995E-07], "Outputs" : [{ "_t" : "BH.oM.Geometry.Vector", "X" : 0.74312442038341175, "Y" : -0.13649135812746502, "Z" : 0.65508488380234986 }], "Name" : "" }, { "_t" : "BH.oM.Test.UnitTests.TestData", "BHoM_Guid" : "0715e066-12d7-4f24-a906-dc233638fe6b", "Inputs" : [{ "_t" : "BH.oM.Geometry.Arc", "CoordinateSystem" : { "_t" : "BH.oM.Geometry.CoordinateSystem.Cartesian", "X" : { "_t" : "BH.oM.Geometry.Vector", "X" : -0.55442430229871953, "Y" : -0.82581113203268319, "Z" : 0.10319722492139127 }, "Y" : { "_t" : "BH.oM.Geometry.Vector", "X" : -0.69598962795040276, "Y" : 0.39209377118942673, "Z" : -0.60154876143161773 }, "Z" : { "_t" : "BH.oM.Geometry.Vector", "X" : 0.45630267455499096, "Y" : -0.40533745053393666, "Z" : -0.79214229806809988 }, "Origin" : { "_t" : "BH.oM.Geometry.Point", "X" : -3.2502648494821749, "Y" : 1.3049630116569531, "Z" : 6.3886366685549145 } }, "Radius" : 11.333395984494089, "StartAngle" : 0.0, "EndAngle" : 3.7966190461293308 }, 9.9999999999999995E-07], "Outputs" : [{ "_t" : "BH.oM.Geometry.Vector", "X" : 0.45630267455499096, "Y" : -0.40533745053393666, "Z" : -0.79214229806809988 }], "Name" : "" }, { "_t" : "BH.oM.Test.UnitTests.TestData", "BHoM_Guid" : "47ff707b-ba0b-4c43-bcdb-44f04ad59cf4", "Inputs" : [{ "_t" : "BH.oM.Geometry.Arc", "CoordinateSystem" : { "_t" : "BH.oM.Geometry.CoordinateSystem.Cartesian", "X" : { "_t" : "BH.oM.Geometry.Vector", "X" : -0.559619923789475, "Y" : -0.030914314634859517, "Z" : -0.8281725943597259 }, "Y" : { "_t" : "BH.oM.Geometry.Vector", "X" : -0.43861144527804469, "Y" : -0.83683048637101398, "Z" : 0.3276198057980575 }, "Z" : { "_t" : "BH.oM.Geometry.Vector", "X" : -0.70316821669424656, "Y" : 0.54658854930441869, "Z" : 0.4547476407858802 }, "Origin" : { "_t" : "BH.oM.Geometry.Point", "X" : -0.40544176076285088, "Y" : 5.8015415686514062, "Z" : 1.3732664997810815 } }, "Radius" : 11.528698973091378, "StartAngle" : 0.0, "EndAngle" : 5.8183909543381542 }, 9.9999999999999995E-07], "Outputs" : [{ "_t" : "BH.oM.Geometry.Vector", "X" : -0.70316821669424656, "Y" : 0.54658854930441869, "Z" : 0.4547476407858802 }], "Name" : "" }, { "_t" : "BH.oM.Test.UnitTests.TestData", "BHoM_Guid" : "dd3f39d2-9654-40a0-b9f6-3499d5d41f03", "Inputs" : [{ "_t" : "BH.oM.Geometry.Arc", "CoordinateSystem" : { "_t" : "BH.oM.Geometry.CoordinateSystem.Cartesian", "X" : { "_t" : "BH.oM.Geometry.Vector", "X" : 0.52540369867954684, "Y" : 0.59925371824799945, "Z" : -0.60402477977298175 }, "Y" : { "_t" : "BH.oM.Geometry.Vector", "X" : 0.80666403207977999, "Y" : -0.12501833105855173, "Z" : 0.57763617982959303 }, "Z" : { "_t" : "BH.oM.Geometry.Vector", "X" : 0.2706364586722263, "Y" : -0.79073724970136661, "Z" : -0.54908151414163886 }, "Origin" : { "_t" : "BH.oM.Geometry.Point", "X" : 3.1407420707861333, "Y" : -3.8786579377475703, "Z" : -1.2529521928258207 } }, "Radius" : 12.775896535402342, "StartAngle" : 0.0, "EndAngle" : 4.5742851129979574 }, 9.9999999999999995E-07], "Outputs" : [{ "_t" : "BH.oM.Geometry.Vector", "X" : 0.2706364586722263, "Y" : -0.79073724970136661, "Z" : -0.54908151414163886 }], "Name" : "" }, { "_t" : "BH.oM.Test.UnitTests.TestData", "BHoM_Guid" : "ce10bf0e-cf33-4774-b1f5-cafe37ea1f1b", "Inputs" : [{ "_t" : "BH.oM.Geometry.Arc", "CoordinateSystem" : { "_t" : "BH.oM.Geometry.CoordinateSystem.Cartesian", "X" : { "_t" : "BH.oM.Geometry.Vector", "X" : 0.48637632194031594, "Y" : -0.60417315923832104, "Z" : 0.63119954619105711 }, "Y" : { "_t" : "BH.oM.Geometry.Vector", "X" : -0.69724149769151678, "Y" : -0.70374907482416083, "Z" : -0.13635077403897675 }, "Z" : { "_t" : "BH.oM.Geometry.Vector", "X" : 0.52658557457710564, "Y" : -0.37378072895766573, "Z" : -0.7635414849942177 }, "Origin" : { "_t" : "BH.oM.Geometry.Point", "X" : 2.1695278190999394, "Y" : -1.7382781254200663, "Z" : -1.7647851824712826 } }, "Radius" : 13.011699014295152, "StartAngle" : 0.0, "EndAngle" : 4.4994914019641579 }, 9.9999999999999995E-07], "Outputs" : [{ "_t" : "BH.oM.Geometry.Vector", "X" : 0.52658557457710564, "Y" : -0.37378072895766573, "Z" : -0.7635414849942177 }], "Name" : "" }, { "_t" : "BH.oM.Test.UnitTests.TestData", "BHoM_Guid" : "3dd80937-a8e2-4aba-9d94-88e078866ff7", "Inputs" : [{ "_t" : "BH.oM.Geometry.Arc", "CoordinateSystem" : { "_t" : "BH.oM.Geometry.CoordinateSystem.Cartesian", "X" : { "_t" : "BH.oM.Geometry.Vector", "X" : -0.87473895280418668, "Y" : -0.098508456350900192, "Z" : -0.47447639401175462 }, "Y" : { "_t" : "BH.oM.Geometry.Vector", "X" : 0.48403874101767858, "Y" : -0.22448963441461964, "Z" : -0.84576054603794992 }, "Z" : { "_t" : "BH.oM.Geometry.Vector", "X" : -0.023200466397372915, "Y" : -0.96948465076439116, "Z" : 0.24405173691492374 }, "Origin" : { "_t" : "BH.oM.Geometry.Point", "X" : -1.4523950591113965, "Y" : -7.2240792875972604, "Z" : -4.342672637494168 } }, "Radius" : 9.4272504456162078, "StartAngle" : 0.0, "EndAngle" : 3.8195003271653092 }, 9.9999999999999995E-07], "Outputs" : [{ "_t" : "BH.oM.Geometry.Vector", "X" : -0.023200466397372915, "Y" : -0.96948465076439116, "Z" : 0.24405173691492374 }], "Name" : "" }, { "_t" : "BH.oM.Test.UnitTests.TestData", "BHoM_Guid" : "54ba28a9-f966-45ef-b0ac-3235bccaa432", "Inputs" : [{ "_t" : "BH.oM.Geometry.Arc", "CoordinateSystem" : { "_t" : "BH.oM.Geometry.CoordinateSystem.Cartesian", "X" : { "_t" : "BH.oM.Geometry.Vector", "X" : -0.8238686017068364, "Y" : -0.4205317817536281, "Z" : 0.37999150997981662 }, "Y" : { "_t" : "BH.oM.Geometry.Vector", "X" : 0.5567044320510981, "Y" : -0.72627226736714501, "Z" : 0.4032477761724802 }, "Z" : { "_t" : "BH.oM.Geometry.Vector", "X" : 0.1063987897313052, "Y" : 0.54376613924416561, "Z" : 0.83246482409481326 }, "Origin" : { "_t" : "BH.oM.Geometry.Point", "X" : -5.7723300877729997, "Y" : 4.5717522723184452, "Z" : 6.5893614306816675 } }, "Radius" : 5.0930823118143032, "StartAngle" : 0.0, "EndAngle" : 3.6344646055027154 }, 9.9999999999999995E-07], "Outputs" : [{ "_t" : "BH.oM.Geometry.Vector", "X" : 0.1063987897313052, "Y" : 0.54376613924416561, "Z" : 0.83246482409481326 }], "Name" : "" }, { "_t" : "BH.oM.Test.UnitTests.TestData", "BHoM_Guid" : "a42079ef-4a3d-43b8-b1c0-d1f3902ec9cd", "Inputs" : [{ "_t" : "BH.oM.Geometry.Arc", "CoordinateSystem" : { "_t" : "BH.oM.Geometry.CoordinateSystem.Cartesian", "X" : { "_t" : "BH.oM.Geometry.Vector", "X" : 0.90671494960916821, "Y" : 0.062329922482514781, "Z" : -0.41711267173099331 }, "Y" : { "_t" : "BH.oM.Geometry.Vector", "X" : 0.30380445035268172, "Y" : -0.78252143344102842, "Z" : 0.54347314758992749 }, "Z" : { "_t" : "BH.oM.Geometry.Vector", "X" : -0.2925249666287455, "Y" : -0.61949591360131007, "Z" : -0.72845998993090177 }, "Origin" : { "_t" : "BH.oM.Geometry.Point", "X" : -8.9781095564735125, "Y" : -1.1517884899822477, "Z" : 3.3535585661112637 } }, "Radius" : 9.4929185415945376, "StartAngle" : 0.0, "EndAngle" : 5.6580605666584258 }, 9.9999999999999995E-07], "Outputs" : [{ "_t" : "BH.oM.Geometry.Vector", "X" : -0.2925249666287455, "Y" : -0.61949591360131007, "Z" : -0.72845998993090177 }], "Name" : "" }, { "_t" : "BH.oM.Test.UnitTests.TestData", "BHoM_Guid" : "7787f7c5-a42e-47b5-b5e4-668a9c206c44", "Inputs" : [{ "_t" : "BH.oM.Geometry.Arc", "CoordinateSystem" : { "_t" : "BH.oM.Geometry.CoordinateSystem.Cartesian", "X" : { "_t" : "BH.oM.Geometry.Vector", "X" : 0.034157058542363325, "Y" : -0.17635715467715751, "Z" : 0.98373342392434293 }, "Y" : { "_t" : "BH.oM.Geometry.Vector", "X" : 0.37167864901379483, "Y" : 0.9159494079973195, "Z" : 0.15129991360420667 }, "Z" : { "_t" : "BH.oM.Geometry.Vector", "X" : -0.92773286953681566, "Y" : 0.36046474998748113, "Z" : 0.096834326545130231 }, "Origin" : { "_t" : "BH.oM.Geometry.Point", "X" : -1.6776150113129971, "Y" : -1.8471657001338015, "Z" : 2.7163196980828115 } }, "Radius" : 6.0799714647248306, "StartAngle" : 0.0, "EndAngle" : 4.1880937922452581 }, 9.9999999999999995E-07], "Outputs" : [{ "_t" : "BH.oM.Geometry.Vector", "X" : -0.92773286953681566, "Y" : 0.36046474998748113, "Z" : 0.096834326545130231 }], "Name" : "" }], "BHoM_Guid" : "ff950275-aaf9-46e3-9db5-e49cd672ed42", "Name" : "" }], "BHoM_Guid" : "60f11806-4211-4f26-850f-736c22a62510", "Name" : "Normal", "_bhomVersion" : "8.2" }